crapssim/__init__.py
crapssim/bet.py
crapssim/dice.py
crapssim/point.py
crapssim/py.typed
crapssim/table.py
crapssim/strategy/__init__.py
crapssim/strategy/examples.py
crapssim/strategy/odds.py
crapssim/strategy/single_bet.py
crapssim/strategy/tools.py
crapssim-0.4.0.dist-info/licenses/LICENSE
tests/__init__.py
tests/integration/__init__.py
tests/integration/test_bet.py
tests/integration/test_dicedoctor_integration.py
tests/integration/test_doc_examples.py
tests/integration/test_dontpass_integration.py
tests/integration/test_examples_smoke.py
tests/integration/test_hammerlock_integration.py
tests/integration/test_ironcross_integration.py
tests/integration/test_knockout_integration.py
tests/integration/test_layodds_integration.py
tests/integration/test_pass2come_integration.py
tests/integration/test_passline_integration.py
tests/integration/test_passline_odds2_integration.py
tests/integration/test_passline_odds345_integration.py
tests/integration/test_passline_odds_integration.py
tests/integration/test_put_integration.py
tests/integration/test_readme.py
tests/integration/test_risk12_integration.py
tests/integration/test_strategy.py
tests/integration/test_strategy_single_bet.py
tests/integration/test_table.py
tests/integration/test_vxp_baseline.py
tests/unit/__init__.py
tests/unit/test_bet.py
tests/unit/test_buy_lay.py
tests/unit/test_commission.py
tests/unit/test_dice.py
tests/unit/test_player.py
tests/unit/test_strategy.py
tests/unit/test_table.py
crapssim-0.4.0.dist-info/METADATA
crapssim-0.4.0.dist-info/WHEEL
crapssim-0.4.0.dist-info/top_level.txt
crapssim-0.4.0.dist-info/RECORD
