Metadata-Version: 2.4
Name: crapssim
Version: 0.4.0
Summary: Simulator for Craps with various betting strategies
Home-page: https://github.com/skent259/CrapsSim
Author: "Sean Kent, @amortization, @nova-rey"
Author-email: skent259@gmail.com
Project-URL: Bug Tracker, https://github.com/skent259/CrapsSim/issues
Classifier: Programming Language :: Python :: 3
Classifier: License :: OSI Approved :: MIT License
Classifier: Operating System :: OS Independent
Requires-Python: >=3.10
License-File: LICENSE
Requires-Dist: numpy>=1.18.0
Provides-Extra: testing
Requires-Dist: pytest; extra == "testing"
Dynamic: license-file
